napari_vectorizer/__init__.py
napari_vectorizer/_sample_data.py
napari_vectorizer/_version.py
napari_vectorizer/_widget.py
napari_vectorizer/napari.yaml
napari_vectorizer/_sample_data/conifer/cells.png
napari_vectorizer/_sample_data/conifer/rings.tiff
napari_vectorizer/_sample_data/conifer/thin_section.jpg
napari_vectorizer/_tests/__init__.py
napari_vectorizer/_tests/test_sample_data.py
napari_vectorizer/_tests/test_widget.py
napari_vectorizer-0.0.5.dist-info/licenses/LICENSE
napari_vectorizer-0.0.5.dist-info/METADATA
napari_vectorizer-0.0.5.dist-info/WHEEL
napari_vectorizer-0.0.5.dist-info/entry_points.txt
napari_vectorizer-0.0.5.dist-info/top_level.txt
napari_vectorizer-0.0.5.dist-info/RECORD
