Metadata-Version: 2.4
Name: napari-vectorizer
Version: 0.0.5
Summary: A plugin to convert label layers to vector layers
Author: Nicola Santacroce
Author-email: nicola.santacroce@protonmail.com
License: 
Project-URL: Bug Tracker, https://github.com/tha-santacruz/napari-vectorizer/issues
Project-URL: Documentation, https://github.com/tha-santacruz/napari-vectorizer#README.md
Project-URL: Source Code, https://github.com/tha-santacruz/napari-vectorizer
Project-URL: User Support, https://github.com/tha-santacruz/napari-vectorizer/issues
Classifier: Development Status :: 2 - Pre-Alpha
Classifier: Framework :: napari
Classifier: Intended Audience :: Developers
Classifier: License :: OSI Approved :: BSD License
Classifier: Operating System :: OS Independent
Classifier: Programming Language :: Python
Classifier: Programming Language :: Python :: 3
Classifier: Programming Language :: Python :: 3 :: Only
Classifier: Programming Language :: Python :: 3.9
Classifier: Programming Language :: Python :: 3.10
Classifier: Programming Language :: Python :: 3.11
Classifier: Programming Language :: Python :: 3.12
Classifier: Topic :: Scientific/Engineering :: Image Processing
Requires-Python: >=3.9
License-File: LICENSE
Requires-Dist: napari[all]
Requires-Dist: numpy
Requires-Dist: magicgui
Requires-Dist: qtpy
Requires-Dist: scikit-image
Provides-Extra: testing
Requires-Dist: tox; extra == "testing"
Requires-Dist: pytest; extra == "testing"
Requires-Dist: pytest-cov; extra == "testing"
Requires-Dist: pytest-qt; extra == "testing"
Requires-Dist: napari; extra == "testing"
Requires-Dist: pyqt5; extra == "testing"
Dynamic: license-file
